main.py
findflights-0.1.0.dist-info/METADATA
findflights-0.1.0.dist-info/WHEEL
findflights-0.1.0.dist-info/entry_points.txt
findflights-0.1.0.dist-info/top_level.txt
findflights-0.1.0.dist-info/RECORD
